flake8_debug/__init__.py
flake8_debug/errors.py
flake8_debug/meta.py
flake8_debug/plugin.py
flake8_debug-0.2.0.dist-info/LICENSE.md
flake8_debug-0.2.0.dist-info/METADATA
flake8_debug-0.2.0.dist-info/WHEEL
flake8_debug-0.2.0.dist-info/entry_points.txt
flake8_debug-0.2.0.dist-info/top_level.txt
flake8_debug-0.2.0.dist-info/RECORD
