Metadata-Version: 2.1
Name: flake8-debug
Version: 0.2.0
Summary: Flake8 plugin to forbid debug function usage
Home-page: https://github.com/vyahello/flake8-debug
Author: Vladimir Yahello
Author-email: vyahello@gmail.com
Classifier: Framework :: Flake8
Classifier: Environment :: Console
Classifier: Intended Audience :: Developers
Classifier: License :: OSI Approved :: MIT License
Classifier: Programming Language :: Python
Classifier: Programming Language :: Python :: 3.7
Classifier: Programming Language :: Python :: 3.8
Classifier: Programming Language :: Python :: 3.9
Classifier: Programming Language :: Python :: 3.10
Classifier: Topic :: Software Development :: Libraries :: Python Modules
Classifier: Topic :: Software Development :: Quality Assurance
License-File: LICENSE.md
Requires-Dist: flake8 (>=4.0.1)
Requires-Dist: astpretty (==2.1.0)
